{"stats":{"minecraft:custom":{"minecraft:time_since_rest":3174,"minecraft:crouch_one_cm":140,"minecraft:play_time":3901,"minecraft:sprint_one_cm":2793,"minecraft:walk_one_cm":3214,"minecraft:damage_taken":770,"minecraft:deaths":3,"minecraft:sneak_time":195,"minecraft:drop":5,"minecraft:jump":33,"minecraft:damage_dealt":70,"minecraft:leave_game":1,"minecraft:time_since_death":3150,"minecraft:total_world_time":3901,"minecraft:fly_one_cm":23877},"minecraft:killed_by":{"minecraft:slime":2,"minecraft:zombie_villager":1},"minecraft:dropped":{"minecraft:sandstone":1,"minecraft:piston":1,"minecraft:iron_bars":1,"minecraft:oak_button":1,"minecraft:bedrock":1},"minecraft:used":{"minecraft:bedrock":24,"minecraft:piston":1,"minecraft:iron_bars":8,"minecraft:oak_button":1,"minecraft:sandstone":35}},"DataVersion":3578}